{
  "todos": [
    {
      "content": "지연짱2",
      "is_completed": false,
      "referenced_todos": [
        21,
        19
      ],
      "created_at": "2023-02-26T05:55:20.701Z",
      "updated_at": "2023-02-26T13:53:10.029Z",
      "id": 18
    },
    {
      "content": "asdfasdf",
      "is_completed": true,
      "referenced_todos": [],
      "created_at": "2023-02-26T06:01:55.800Z",
      "updated_at": "2023-02-26T13:53:14.134Z",
      "id": 19
    },
    {
      "content": "zsdfzsfz",
      "is_completed": true,
      "referenced_todos": [],
      "created_at": "2023-02-26T06:01:57.822Z",
      "updated_at": "2023-02-26T13:52:52.875Z",
      "id": 20
    },
    {
      "content": "진호짱",
      "is_completed": false,
      "referenced_todos": [
        18
      ],
      "created_at": "2023-02-26T06:02:03.063Z",
      "updated_at": "2023-02-26T06:02:04.376Z",
      "id": 21
    },
    {
      "content": "sdgdsgsg",
      "referenced_todos": [],
      "created_at": "2023-02-26T06:18:26.301Z",
      "updated_at": "2023-02-26T06:18:26.301Z",
      "is_completed": false,
      "id": 22
    },
    {
      "content": "sdgsdgsdgxcv",
      "referenced_todos": [],
      "created_at": "2023-02-26T06:18:29.449Z",
      "updated_at": "2023-02-26T06:18:29.449Z",
      "is_completed": false,
      "id": 23
    },
    {
      "content": "sfsfsdfsd",
      "referenced_todos": [],
      "created_at": "2023-02-26T06:18:32.962Z",
      "updated_at": "2023-02-26T06:18:32.962Z",
      "is_completed": false,
      "id": 24
    },
    {
      "content": "sdfsdfsdfdsfsdf",
      "referenced_todos": [],
      "created_at": "2023-02-26T06:18:35.693Z",
      "updated_at": "2023-02-26T06:18:35.693Z",
      "is_completed": false,
      "id": 25
    },
    {
      "content": "safxx",
      "referenced_todos": [],
      "created_at": "2023-02-26T06:18:38.555Z",
      "updated_at": "2023-02-26T06:18:38.555Z",
      "is_completed": false,
      "id": 26
    },
    {
      "content": "241515",
      "referenced_todos": [],
      "created_at": "2023-02-26T06:18:41.765Z",
      "updated_at": "2023-02-26T06:18:41.765Z",
      "is_completed": false,
      "id": 27
    },
    {
      "content": "315151351",
      "referenced_todos": [],
      "created_at": "2023-02-26T06:18:46.204Z",
      "updated_at": "2023-02-26T06:18:46.204Z",
      "is_completed": false,
      "id": 28
    },
    {
      "content": "dsfdfsf",
      "referenced_todos": [
        19
      ],
      "created_at": "2023-02-26T09:23:01.285Z",
      "updated_at": "2023-02-26T09:23:01.285Z",
      "is_completed": false,
      "id": 29
    },
    {
      "content": "teststett",
      "referenced_todos": [
        21
      ],
      "created_at": "2023-02-26T09:23:19.899Z",
      "updated_at": "2023-02-26T09:23:19.899Z",
      "is_completed": false,
      "id": 30
    },
    {
      "content": "팡팡팡",
      "referenced_todos": [
        21
      ],
      "created_at": "2023-02-26T09:23:41.636Z",
      "updated_at": "2023-02-26T09:23:41.636Z",
      "is_completed": false,
      "id": 31
    },
    {
      "content": "진호짱ㅉ아ㅉ아ㅉ아ㅉ아ㅉㅇ진호짱ㅉ아ㅉ아ㅉ아ㅉ아ㅉㅇ진호짱ㅉ아ㅉ아ㅉ아ㅉ아ㅉㅇ진호짱ㅉ아ㅉ아ㅉ아ㅉ아ㅉㅇ진호짱ㅉ아ㅉ아ㅉ아ㅉ아ㅉㅇ진호짱ㅉ아ㅉ아ㅉ아ㅉ아ㅉㅇ진호짱ㅉ아ㅉ아ㅉ아ㅉ아ㅉㅇ진호짱ㅉ아ㅉ아ㅉ아ㅉ아ㅉㅇ",
      "referenced_todos": [
        18
      ],
      "created_at": "2023-02-26T13:05:20.529Z",
      "updated_at": "2023-02-26T13:05:20.529Z",
      "is_completed": false,
      "id": 32
    }
  ]
}